{
  "app_title": "皮克敏...的好朋友",
  "app_subtitle": "輸入暱稱後按下按鈕後會抽出一張卡片，並翻面顯示結果。",
  "badge_text": "博愛皮克敏之友團建活動🍄",
  "card_back_image": "images/卡背.png",
  "allow_same_name_once": true,
  "cards": [
    {
      "id": "seat_k20",
      "title": " ",
      "subtitle": "K20",
      "image": "images/紅色皮克敏.png"
    },
    {
      "id": "seat_k21",
      "title": " ",
      "subtitle": "K21",
      "image": "images/黃色皮克敏.png"
    },
    {
      "id": "seat_j15",
      "title": " ",
      "subtitle": "J15",
      "image": "images/藍色皮克敏.png"
    },
    {
      "id": "seat_j16",
      "title": " ",
      "subtitle": "J16",
      "image": "images/石頭皮克敏.png"
    },
    {
      "id": "seat_j17",
      "title": " ",
      "subtitle": "J17",
      "image": "images/紫色皮克敏.png"
    },
    {
      "id": "seat_j18",
      "title": " ",
      "subtitle": "J18",
      "image": "images/蒼蠅皮克敏.png"
    }
  ]
}
